{"datasetSettings": {"randomizedPartitions": true, "partitions": [70, 20, 10], "featureSpecs": {"images": {"iotype": "Input", "datatype": "image", "preprocessing": {"resize": {"mode": "automatic", "type": "mode"}}}, "category": {"iotype": "Target", "datatype": "categorical", "preprocessing": {}}}, "randomSeed": "123", "datasetId": 10}, "trainingSettings": {"Epochs": 100, "Batch_size": 8, "Shuffle": true, "Loss": "Cross-Entropy", "LossOptions": [{"text": "Cross-Entropy", "value": "Cross-Entropy"}, {"text": "Quadratic", "value": "Quadratic"}, {"text": "Dice", "value": "Dice"}], "Learning_rate": 0.001, "Optimizer": "ADAM", "OptimizerOptions": [{"text": "ADAM", "value": "ADAM"}, {"text": "SGD", "value": "SGD"}, {"text": "Adagrad", "value": "Adagrad"}, {"text": "RMSprop", "value": "RMSprop"}], "Beta1": 0.9, "Beta2": 0.999, "Momentum": 0, "Centered": false, "AutoCheckpoint": false}, "graphSettings": {"0": {"Name": "images", "Type": "IoInput", "Properties": {"DataType": "image", "FeatureName": "images"}, "Code": null, "backward_connections": [], "forward_connections": [{"dst_id": "1", "dst_var": "input", "src_var": "output"}], "visited": false, "previewVariable": ""}, "1": {"Name": "Convolution_1", "Type": "DeepLearningConv", "Properties": {"Activation_function": "Sigmoid", "Batch_norm": false, "Conv_dim": "2D", "Conv_type": "Conv", "Dropout": false, "Feature_maps": 8, "Keep_prob": 0, "Padding": "SAME", "Patch_size": 3, "PoolBool": false, "Pool_area": null, "Pool_padding": null, "Pool_stride": null, "Pooling": null, "Stride": 2}, "Code": null, "backward_connections": [{"dst_var": "input", "src_id": "0", "src_var": "output"}], "forward_connections": [{"dst_id": "2", "dst_var": "input", "src_var": "output"}], "visited": false, "previewVariable": ""}, "2": {"Name": "Dense_1", "Type": "DeepLearningFC", "Properties": {"Activation_function": "ReLU", "Batch_norm": false, "Dropout": false, "Keep_prob": 0, "Neurons": 128}, "Code": null, "backward_connections": [{"dst_var": "input", "src_id": "1", "src_var": "output"}], "forward_connections": [{"dst_id": "3", "dst_var": "input", "src_var": "output"}], "visited": false, "previewVariable": ""}, "3": {"Name": "Dense_2", "Type": "DeepLearningFC", "Properties": {"Activation_function": "Softmax", "Batch_norm": false, "Dropout": false, "Keep_prob": 0, "Neurons": 2}, "Code": null, "backward_connections": [{"dst_var": "input", "src_id": "2", "src_var": "output"}], "forward_connections": [{"dst_id": "4", "dst_var": "input", "src_var": "output"}], "visited": false, "previewVariable": ""}, "4": {"Name": "category", "Type": "IoOutput", "Properties": {"DataType": "categorical", "FeatureName": "category"}, "Code": null, "backward_connections": [{"dst_var": "input", "src_id": "3", "src_var": "output"}], "forward_connections": [], "visited": false, "previewVariable": ""}}, "frontendSettings": {"apiMeta": {"model_id": 8, "project": 1, "name": "Defect Data Set", "created": "2022-03-20T20:57:41.725683Z", "updated": "2022-03-20T20:57:41.725683Z", "is_removed": false, "saved_by": "", "location": "C:/Users/sebas/OneDrive - Delft University of Technology/GitHub/AE2223-II-AI\\Defect Data Set", "saved_version_location": "", "datasets": [10]}, "networkName": "Defect Data Set", "networkMeta": {"openStatistics": null, "openTest": null, "hideModel": false, "hideStatistics": false, "hideTest": false, "zoom": 1, "zoomSnapshot": 1, "usingWeights": false, "netMode": "edit", "chartsRequest": {"timerID": null, "waitGlobalEvent": false, "doRequest": 0, "showCharts": 0}}, "networkRootFolder": "", "layerMeta": {"0": {"layerId": "0", "copyId": null, "copyContainerElement": null, "layerType": "IoInput", "layerSettingsTabName": null, "layerCodeError": null, "layerNone": false, "layerMeta": {"isInvisible": false, "isLock": false, "isSelected": false, "position": {"top": 60, "left": 60}, "tutorialId": "", "OutputDim": "512x512x1", "InputDim": "", "layerContainerName": "", "layerBgColor": "", "containerDiff": {"top": 0, "left": 0}}, "chartData": {}, "checkpoint": [], "endPoints": [], "connectionOut": [], "connectionIn": [], "connectionArrow": [], "inputs": {}, "outputs": {"f2514cdc-8070-408f-89c6-335e5ff21b5e": {"name": "output", "reference_var": "output"}}, "previewVariableList": [], "isTrained": false, "isSettingsLocked": false, "chartDataIsLoading": 0}, "1": {"layerId": "1", "copyId": null, "copyContainerElement": null, "layerType": "DeepLearningConv", "layerSettingsTabName": null, "layerCodeError": null, "layerNone": false, "layerMeta": {"isInvisible": false, "isLock": false, "isSelected": false, "position": {"top": 60, "left": 270}, "tutorialId": "", "OutputDim": "256x256x8", "InputDim": "", "layerContainerName": "", "layerBgColor": "", "containerDiff": {"top": 0, "left": 0}}, "chartData": {}, "checkpoint": [], "endPoints": [], "connectionOut": [], "connectionIn": [], "connectionArrow": [], "inputs": {"3453ac8f-bdc0-4960-b427-df7bf9aaeada": {"name": "input", "reference_var_id": "f2514cdc-8070-408f-89c6-335e5ff21b5e", "reference_layer_id": "0", "isDefault": true}}, "outputs": {"acf7daea-bc04-4277-b144-325b8508fe2c": {"name": "output", "reference_var": "output"}}, "previewVariableList": [], "isTrained": false, "isSettingsLocked": false, "chartDataIsLoading": 0}, "2": {"layerId": "2", "copyId": null, "copyContainerElement": null, "layerType": "DeepLearningFC", "layerSettingsTabName": null, "layerCodeError": null, "layerNone": false, "layerMeta": {"isInvisible": false, "isLock": false, "isSelected": false, "position": {"top": 60, "left": 450}, "tutorialId": "", "OutputDim": "128", "InputDim": "", "layerContainerName": "", "layerBgColor": "", "containerDiff": {"top": 0, "left": 0}}, "chartData": {}, "checkpoint": [], "endPoints": [], "connectionOut": [], "connectionIn": [], "connectionArrow": [], "inputs": {"b3a9c2a5-651d-4607-939d-ef21debc8a20": {"name": "input", "reference_var_id": "acf7daea-bc04-4277-b144-325b8508fe2c", "reference_layer_id": "1", "isDefault": true}}, "outputs": {"d98b9dae-8679-4967-9875-313865d1a185": {"name": "output", "reference_var": "output"}}, "previewVariableList": [], "isTrained": false, "isSettingsLocked": false, "chartDataIsLoading": 0}, "3": {"layerId": "3", "copyId": null, "copyContainerElement": null, "layerType": "DeepLearningFC", "layerSettingsTabName": null, "layerCodeError": null, "layerNone": false, "layerMeta": {"isInvisible": false, "isLock": false, "isSelected": false, "position": {"top": 60, "left": 660}, "tutorialId": "", "OutputDim": "2", "InputDim": "", "layerContainerName": "", "layerBgColor": "", "containerDiff": {"top": 0, "left": 0}}, "chartData": {}, "checkpoint": [], "endPoints": [], "connectionOut": [], "connectionIn": [], "connectionArrow": [], "inputs": {"a4fece3d-c4af-4e4c-abf1-5b052420fb95": {"name": "input", "reference_var_id": "d98b9dae-8679-4967-9875-313865d1a185", "reference_layer_id": "2", "isDefault": true}}, "outputs": {"e048dac2-d525-495d-a031-2435130f66f0": {"name": "output", "reference_var": "output"}}, "previewVariableList": [], "isTrained": false, "isSettingsLocked": false, "chartDataIsLoading": 0}, "4": {"layerId": "4", "copyId": null, "copyContainerElement": null, "layerType": "IoOutput", "layerSettingsTabName": null, "layerCodeError": null, "layerNone": false, "layerMeta": {"isInvisible": false, "isLock": false, "isSelected": false, "position": {"top": 60, "left": 870}, "tutorialId": "", "OutputDim": "2", "InputDim": "", "layerContainerName": "", "layerBgColor": "", "containerDiff": {"top": 0, "left": 0}}, "chartData": {}, "checkpoint": [], "endPoints": [], "connectionOut": [], "connectionIn": [], "connectionArrow": [], "inputs": {"3c97f3bb-84bb-41e5-9ef9-b7e29d530216": {"name": "input", "reference_var_id": "e048dac2-d525-495d-a031-2435130f66f0", "reference_layer_id": "3", "isDefault": true}}, "outputs": {}, "previewVariableList": [], "isTrained": false, "isSettingsLocked": false, "chartDataIsLoading": 0}}}}